mysodexo/__init__.py
mysodexo/api.py
mysodexo/cli.py
mysodexo/constants.py
mysodexo/sodexows.mo2o.com_client-android.crt.pem
mysodexo/sodexows.mo2o.com_client-android.key.pem
mysodexo-20221022.dist-info/LICENSE
mysodexo-20221022.dist-info/METADATA
mysodexo-20221022.dist-info/WHEEL
mysodexo-20221022.dist-info/entry_points.txt
mysodexo-20221022.dist-info/top_level.txt
mysodexo-20221022.dist-info/RECORD
